hug_raven
