Metadata-Version: 1.0
Name: hug-raven
Version: 1.1.0
Summary: Hug integration for Sentry
Home-page: https://github.com/banteg/hug_raven
Author: banteg
Author-email: UNKNOWN
License: UNKNOWN
Platform: UNKNOWN
